Metadata-Version: 2.1
Name: regulator
Version: 1.0.0
Summary: regular express module
Author: gadapokasoz6
